yotpo_api.py
yotpo_api-0.0.5.dist-info/LICENSE
yotpo_api-0.0.5.dist-info/METADATA
yotpo_api-0.0.5.dist-info/WHEEL
yotpo_api-0.0.5.dist-info/top_level.txt
yotpo_api-0.0.5.dist-info/RECORD
