Metadata-Version: 2.1
Name: yotpo-api
Version: 0.0.5
Summary: yotpo api integration
Home-page: https://github.com/atanasoff-yordan/yotpo_api
Author: yordan atanasoff
Author-email: atanasoff.yordan@gmail.com
License: UNKNOWN
Project-URL: Bug Tracker, https://github.com/atanasoff-yordan/yotpo_api/issues
Platform: UNKNOWN
Classifier: Programming Language :: Python :: 3
Classifier: License :: OSI Approved :: MIT License
Classifier: Operating System :: OS Independent
Requires-Python: >=3.7
Requires-Dist: python-dateutil
Requires-Dist: requests
Provides-Extra: dev
Requires-Dist: black ; extra == 'dev'
Requires-Dist: pytest (>=3.7) ; extra == 'dev'
